{
  "theChaser:Acid Potion": {
    "NAME": "瓶装出血",
    "DESCRIPTIONS": [
      "给予敌人 #b",
      " 层 #y出血 。"
    ]
  },
        "theChaser:Shadow Potion": {
                "NAME": "罐子里的影子",
                "DESCRIPTIONS": [
                        "#y隐身 #b",
                        " 回合。"
                ]
        },
        "theChaser:Target Potion": {
                "NAME": "瞄准药水",
                "DESCRIPTIONS": [
                        "#y瞄准 #b",
                        " 次。"
                ]
        }
}
