{
	"theChaser:Throwing Knife": {
		"NAME": "匕首",
		"DESCRIPTION": "虚无 。 NL 随机对敌人造成 !D! 点伤害。 受 thechaser:靶子 影响的敌人优先。 消耗 。"
	},
	"theChaser:Bloody Wind": {
		"NAME": "血腥风",
		"DESCRIPTION": "给予所有敌人 !M! 层 thechaser:出血 。"
	},
	"theChaser:Camouflage": {
		"NAME": "伪装",
		"DESCRIPTION": "获得 1 层 thechaser:假伤 !M! 次。"
	},
	"theChaser:Followup Slash": {
		"NAME": "后续斜线",
		"DESCRIPTION": "虚无 。 造成 !D! 点伤害2次。 NL 消耗 。"
	},
	"theChaser:Knife Throw": {
		"NAME": "飞刀",
		"DESCRIPTION": "thechaser:瞄准 !M! 次。"
	},
	"theChaser:Sequence Flow": {
		"NAME": "序列流",
		"DESCRIPTION": "虚无 。 造成 !D! 点伤害。 NL 消耗 。"
	},
	"theChaser:Reactive Shot": {
		"NAME": "反应射击",
		"DESCRIPTION": "随机对敌人造成 !D! 点伤害，给予 !M! 层 thechaser:靶子 。"
	},
	"theChaser:Flawed Stealth": {
		"NAME": "隐士",
		"DESCRIPTION": "获得 !B! 点 格挡 。 NL 获得1点 脆弱 。"
	},
	"theChaser:Strike": {
		"NAME": "打击",
		"DESCRIPTION": "造成 !D! 点伤害。"
	},
	"theChaser:Defend": {
		"NAME": "防御",
		"DESCRIPTION": "获得 !B! 点 格挡 。"
	},
	"theChaser:Alert": {
		"NAME": "警觉",
		"DESCRIPTION": "获得 !B! 点 格挡 。 NL 获得 1 层 假伤 !M! 次。 NL thechaser:谍报 !M! 。"
	},
	"theChaser:Blitzkrieg": {
		"NAME": "闪电战",
		"DESCRIPTION": "造成 !D! 点伤害。 NL 给予 !M! 层 thechaser:无防备 。"
	},
	"theChaser:Brass": {
		"NAME": "黄铜轨道",
		"DESCRIPTION": "给予 !M! 层 thechaser:出血 。"
	},
	"theChaser:Chase": {
		"NAME": "追踪",
		"DESCRIPTION": "造成 !D! 点伤害。 每有一个受到 thechaser:靶子 影响的敌人、抽1张牌。"
	},
	"theChaser:Continuous Slash": {
		"NAME": "连续斜线",
		"DESCRIPTION": "造成 !D! 点伤害2次。 NL thechaser:迅速 : 增加一张 *后续斜线 到你的手牌。",
		"UPGRADE_DESCRIPTION": "造成 !D! 点伤害2次。 NL thechaser:迅速 : 增加一张 *后续斜线+ 到你的手牌。"
	},
	"theChaser:Delusive Strike": {
		"NAME": "幻术打击",
		"DESCRIPTION": "造成 !D! 点伤害。 NL 如果您受到 虚弱 的影响，获得 [E] [E] 。"
	},
	"theChaser:Fatal Blitz": {
		"NAME": "致命闪电战",
		"DESCRIPTION": "造成 !D! 点伤害。 NL 给予 !M! 层 thechaser:出血 。"
	},
	"theChaser:Geck": {
		"NAME": "使防御无效",
		"DESCRIPTION": "给予所有敌人 !M! 层 thechaser:无防备 和 thechaser:靶子 。"
	},
	"theChaser:Inertial Strike": {
		"NAME": "惯性打击",
		"DESCRIPTION": "造成 !D! 点伤害。 NL 造成等同于本回合打出的张牌数量的额外点伤害。",
		"EXTENDED_DESCRIPTION": [
			"造成 !D! 点伤害。 NL 造成等同于本回合打出的张牌数量的额外点伤害。(",
			" 的卡牌)."
		]
	},
	"theChaser:Leave Traces": {
		"NAME": "留下一个标记",
		"DESCRIPTION": "对所有敌人造成 !D! 点伤害并给予 !M! 层 thechaser:靶子 。"
	},
	"theChaser:Linger": {
		"NAME": "恶意把戏",
		"DESCRIPTION": "获得 !B! 点 格挡 。 NL thechaser:瞄准 !M! 次。"
	},
	"theChaser:Makeready": {
		"NAME": "准备",
		"DESCRIPTION": "抽 !M! 张牌。如果这张牌是你本回合打出的第一张牌，再抽一张牌。"
	},
	"theChaser:Passing": {
		"NAME": "通过",
		"DESCRIPTION": "获得 !B! 点 格挡 。 如果你在本回合 thechaser:瞄准 ，抽2张牌。"
	},
	"theChaser:Random Throw": {
		"NAME": "匕首横冲直撞",
		"DESCRIPTION": "增加 !M! 张 *后续斜线 到你的手牌。"
	},
	"theChaser:Scar Stab": {
		"NAME": "刺伤",
		"DESCRIPTION": "造成 !D! 点伤害。 NL 如果敌人受到 thechaser:出血 的影响，触发它。",
		"UPGRADE_DESCRIPTION": "造成 !D! 点伤害。 NL 如果敌人受到 thechaser:出血 的影响，触发它2次。"
	},
	"theChaser:Stalling": {
		"NAME": "拖延",
		"DESCRIPTION": "造成 !D! 点伤害。 NL 获得 1 层 thechaser:假伤 !M! 次。 NL thechaser:谍报 !M!."
	},
	"theChaser:Thornmail": {
		"NAME": "刺甲",
		"DESCRIPTION": "获得 !B! 点 格挡 。 NL 给予所有敌人 !M! 层 thechaser:出血 。"
	},
	"theChaser:Watch": {
		"NAME": "留意",
		"DESCRIPTION": "给予 !M! 层 thechaser:靶子 。 NL 消耗 。"
	},
	"theChaser:Wound": {
		"NAME": "打开静脉",
		"DESCRIPTION": "造成 !D! 点伤害。 NL 给予 !M! 层 thechaser:出血 。"
	},
	"theChaser:Aggravate": {
		"NAME": "加剧",
		"DESCRIPTION": "获得 !B! 点 格挡 。 NL 对所有受到 thechaser:出血 影响的敌人触发 thechaser:出血 。"
	},
	"theChaser:Attack First": {
		"NAME": "先攻",
		"DESCRIPTION": "获得 [E] [E] 。 NL 在下一回合少抽 !M! 张牌。"
	},
	"theChaser:Big Picture": {
		"NAME": "宏伟计划",
		"DESCRIPTION": "每当你对自己施获得负面状态，获得 !M! 点 力量 。"
	},
	"theChaser:Break Armour": {
		"NAME": "摧毁盔甲",
		"DESCRIPTION": "Remove ALL stacks of thechaser:Targeting on the enemy. Apply Vulnerable, Weak, and thechaser:Bleeding equal to the amount removed. 消耗 。",
		"UPGRADE_DESCRIPTION": "Apply Vulnerable, Weak, and thechaser:Bleeding equal to the amount of thechaser:Targeting on the enemy. 消耗 。"
	},
	"theChaser:Bulwark": {
		"NAME": "空降",
		"DESCRIPTION": "获得 !M! 点 力量 。 NL 获得 !M! 点 敏捷 。"
	},
	"theChaser:Chance": {
		"NAME": "示踪者的运气",
		"DESCRIPTION": "获得 !B! 点 格挡 。 NL thechaser:迅速 : Reduce the cost of a random card in your hand to 0 this turn."
	},
	"theChaser:Conquest": {
		"NAME": "征服精神",
		"DESCRIPTION": "Gain Strength equal to the cumulative stacks of ALL debuffs you have. NL 消耗 。",
		"UPGRADE_DESCRIPTION": "Gain Strength equal to the cumulative stacks of ALL debuffs you have.",
		"EXTENDED_DESCRIPTION": [
			"Gain Strength equal to the cumulative stacks of ALL debuffs you have (",
			" Strength).",
			" NL 消耗 。"
		]
	},
	"theChaser:Diplade": {
		"NAME": "双刀片",
		"DESCRIPTION": "Whenever you play a Skill that doesn't cost 0, add 1 *Throwing *Knife to your hand."
	},
	"theChaser:Disguise": {
		"NAME": "遮盖",
		"DESCRIPTION": "获得 !B! 点 格挡 。 NL Repeat for each unique debuff on you.",
		"EXTENDED_DESCRIPTION": [
			"获得 !B! 点 格挡 。 NL Repeat for each unique debuff on you (",
			" debuffs)."
		]
	},
	"theChaser:Fall Technique": {
		"NAME": "摔倒技巧",
		"DESCRIPTION": "获得 !B! 点 格挡 。 NL Gain !M! Weak."
	},
	"theChaser:Feeble Defend": {
		"NAME": "欺骗性防御",
		"DESCRIPTION": "获得 !B! 点 格挡 。 NL If you are Frail, double the amount of Block gained.",
		"UPGRADE_DESCRIPTION": "获得 !B! 点 格挡 。 NL If you are Frail, triple the amount of Block gained."
	},
	"theChaser:Feeble Strike": {
		"NAME": "欺骗性打击",
		"DESCRIPTION": "造成 !D! 点伤害。 NL If you are Weak, deal double damage.",
		"UPGRADE_DESCRIPTION": "造成 !D! 点伤害。 NL If you are Weak, deal triple damage."
	},
	"theChaser:Flexibility": {
		"NAME": "灵活性",
		"DESCRIPTION": "Choose two: NL Trigger thechaser:Targeting !M! times; gain thechaser:Proxy !M! times; apply !M! thechaser:Bleeding to ALL enemies. NL 消耗 。"
	},
	"theChaser:Gale Strike": {
		"NAME": "风暴打击",
		"DESCRIPTION": "Deal !D! damage X times to ALL enemies. Trigger thechaser:Targeting X times."
	},
	"theChaser:Hack": {
		"NAME": "多次刺伤",
		"DESCRIPTION": "Deal !D! damage !M! times."
	},
	"theChaser:Hidden Dagger": {
		"NAME": "隐藏的匕首",
		"DESCRIPTION": "获得 !B! 点 格挡 。 Add !M! *Throwing *Knife into your hand. NL thechaser:迅速 : Upgrade ALL *Throwing *Knife cards in your hand."
	},
	"theChaser:Internal Hemorrhage": {
		"NAME": "内部出血",
		"DESCRIPTION": "Apply !M! thechaser:Bleeding and 2 Weak to ALL enemies. NL 消耗 。"
	},
	"theChaser:Open Sore": {
		"NAME": "开放性疮",
		"DESCRIPTION": "At the start of your turn, apply !M! thechaser:Bleeding to ALL enemies."
	},
	"theChaser:Paralyze": {
		"NAME": "瘫痪",
		"DESCRIPTION": "Enemy loses Strength equal to the amount of unique debuffs on them. NL 消耗 。"
	},
	"theChaser:Penetrate": {
		"NAME": "穿透射击",
		"DESCRIPTION": "Deal !D! damage and apply !M! Vulnerable. If the enemy is already Vulnerable, apply !M! thechaser:Blindsided instead."
	},
	"theChaser:Penetrative": {
		"NAME": "刺耳的打击",
		"DESCRIPTION": "Whenever you deal damage by triggering thechaser:Targeting, deal !M! additional damage."
	},
	"theChaser:Pluck Out Daggers": {
		"NAME": "拔出匕首",
		"DESCRIPTION": "Costs 1 [E] less for each time you have triggered thechaser:Targeting this turn. NL Deal !D! damage !M! times."
	},
	"theChaser:Ragewind": {
		"NAME": "狂暴之风",
		"DESCRIPTION": "Trigger thechaser:Targeting !M! times. NL Permanently increase this card's thechaser:Targeting trigger amount by 1. NL 消耗 。"
	},
	"theChaser:Ready To Counter": {
		"NAME": "准备反击",
		"DESCRIPTION": "获得 !B! 点 格挡 X times. Trigger thechaser:Targeting X times."
	},
	"theChaser:Replica Dagger": {
		"NAME": "复制匕首",
		"DESCRIPTION": "At the start of your turn, add a *Throwing *Knife into your hand and apply 1 thechaser:Targeting to a random enemy.",
		"UPGRADE_DESCRIPTION": "固有 。 NL At the start of your turn, add a *Throwing *Knife into your hand and apply 1 thechaser:Targeting to a random enemy."
	},
	"theChaser:Secret Card": {
		"NAME": "示踪者的诡计",
		"DESCRIPTION": "Draw 1 card. NL If it's an Attack, trigger thechaser:Targeting !M! times."
	},
	"theChaser:Sequence": {
		"NAME": "斜线序列",
		"DESCRIPTION": "造成 !D! 点伤害。 NL Add !M! *Sequence *Flow into your hand. NL thechaser:迅速 : Deal !D! damage 2 times."
	},
	"theChaser:Space Out": {
		"NAME": "战斗间隔",
		"DESCRIPTION": "Whenever you trigger thechaser:Targeting, gain !M! Block."
	},
	"theChaser:Testing": {
		"NAME": "技能测试",
		"DESCRIPTION": "Deal !D! damage and apply !M! Vulnerable to ALL enemies."
	},
	"theChaser:Throes": {
		"NAME": "愤怒的阵阵",
		"DESCRIPTION": "Deal !D! damage and apply !M! thechaser:Blindsided. NL Gain 1 Vulnerable."
	},
	"theChaser:Unstable Block": {
		"NAME": "不稳定的防御",
		"DESCRIPTION": "获得 !B! 点 格挡 。and !M! Vulnerable.",
		"UPGRADE_DESCRIPTION": "获得 !B! 点 格挡 。and !M! thechaser:Blindsided."
	},
	"theChaser:Weakness Strike": {
		"NAME": "弱点打击",
		"DESCRIPTION": "造成 !D! 点伤害。 Repeat for each unique debuff on the enemy."
	},
	"theChaser:Win The Exchange": {
		"NAME": "赢得交流",
		"DESCRIPTION": "造成 !D! 点伤害。 NL If the enemy has thechaser:Blindsided, gain [E] and draw 1 card."
	},
	"theChaser:Wither": {
		"NAME": "萎缩",
		"DESCRIPTION": "Apply 99 Weak. 消耗 。"
	},
	"theChaser:Absolute Advantage": {
		"NAME": "绝对优势",
		"DESCRIPTION": "Gain [E]. NL Draw 1 card for each unique debuff on ALL enemies. NL 消耗 。",
		"UPGRADE_DESCRIPTION": "Gain [E] [E]. NL Draw 1 card for each unique debuff on ALL enemies. NL 消耗 。"
	},
	"theChaser:Acceleration": {
		"NAME": "加速",
		"DESCRIPTION": "Whenever you play an Attack, gain !M! temporary Strength."
	},
	"theChaser:Approach Run": {
		"NAME": "助跑",
		"DESCRIPTION": "thechaser:谍报 !M!. NL thechaser:迅速 : Apply !M! thechaser:Bleeding to ALL enemies. NL 消耗 。"
	},
	"theChaser:Dual Wielding": {
		"NAME": "双手",
		"DESCRIPTION": "Whenever you trigger thechaser:Targeting this turn, trigger it twice."
	},
	"theChaser:Forte Is Frailty": {
		"NAME": "权力欲",
		"DESCRIPTION": "All your buffs count as debuffs, for the purposes of effects which check for debuffs on you."
	},
	"theChaser:Fraudulence": {
		"NAME": "示踪者的守护",
		"DESCRIPTION": "获得 !B! 点 格挡 。for each unique debuff on ALL enemies."
	},
	"theChaser:Hide": {
		"NAME": "完美的隐身",
		"DESCRIPTION": "thechaser:Hide for !M! turns. NL 消耗 。"
	},
	"theChaser:Incisive Blade": {
		"NAME": "颈刀",
		"DESCRIPTION": "虚无 。 造成 !D! 点伤害。 NL 消耗 。"
	},
	"theChaser:Phrenitis": {
		"NAME": "错乱",
		"DESCRIPTION": "Apply 1 Weak, Vulnerable, Frail, Poison, thechaser:Bleeding, thechaser:Targeting, thechaser:Proxy, and thechaser:Blindsided. NL 消耗 。"
	},
	"theChaser:Preemptive Attack": {
		"NAME": "先发制人",
		"DESCRIPTION": "At the start of your turn, draw 1 additional card and trigger thechaser:Targeting once."
	},
	"theChaser:Prepay": {
		"NAME": "先付",
		"DESCRIPTION": "This turn, your next X cards cost 0. 消耗 。",
		"UPGRADE_DESCRIPTION": "This turn, your next X cards cost 0. Draw X cards. 消耗 。"
	},
	"theChaser:Saw Blade": {
		"NAME": "锯齿",
		"DESCRIPTION": "Whenever you play a card, apply !M! thechaser:Bleeding to ALL enemies.",
		"UPGRADE_DESCRIPTION": "固有 。 Whenever you play a card, apply !M! thechaser:Bleeding to ALL enemies."
	},
	"theChaser:Shadow Form": {
		"NAME": "Spectre Form",
		"DESCRIPTION": "At the start of your turn, increase damage dealt when triggering thechaser:Targeting by !M!."
	},
	"theChaser:Stealage": {
		"NAME": "偷盗",
		"DESCRIPTION": "造成 !D! 点伤害。 NL Gain !M! Gold. NL 消耗 。"
	},
	"theChaser:Unwary": {
		"NAME": "失神",
		"DESCRIPTION": "Dealing damage by triggering thechaser:Targeting also applies thechaser:Blindsided."
	},
	"theChaser:Vitality": {
		"NAME": "活力",
		"DESCRIPTION": "Heal HP equal to the amount of times you have triggered thechaser:Targeting this turn. NL 消耗 。",
		"UPGRADE_DESCRIPTION": "Retain. NL Heal HP equal to the amount of times you have triggered thechaser:Targeting this turn. NL 消耗 。",
		"EXTENDED_DESCRIPTION": [
			"Heal HP equal to the amount of times you have triggered thechaser:Targeting this turn (",
			" HP healed). NL 消耗 。",
			"Retain. NL"
		]
	},
	"theChaser:Walkout": {
		"NAME": "退场",
		"DESCRIPTION": "Deal !D! damage to ALL enemies. Trigger thechaser:Targeting equal to the amount of cards played this turn. NL End your turn.",
		"EXTENDED_DESCRIPTION": [
			"Deal !D! damage to ALL enemies. Trigger thechaser:Targeting equal to the amount of cards played this turn (",
			" cards). NL End your turn."
		]
	},
	"theChaser:Wile": {
		"NAME": "残酷的毁灭",
		"DESCRIPTION": "造成 !D! 点伤害。 NL Apply !M! Vulnerable, Weak, and thechaser:Blindsided."
	},


	"theChaser:A": {
		"NAME": "",
		"DESCRIPTION": ""
	},
	"theChaser:B": {
		"NAME": "",
		"DESCRIPTION": "",
		"UPGRADE_DESCRIPTION": ""
	},
	"theChaser:C": {
		"NAME": "",
		"DESCRIPTION": "",
		"EXTENDED_DESCRIPTION": [
			"",
			""
		]
	},
	"theChaser:D": {
		"NAME": "",
		"DESCRIPTION": "",
		"UPGRADE_DESCRIPTION": "",
		"EXTENDED_DESCRIPTION": [
			"",
			""
		]
	}
}